pg_cache/__init__.py
pg_cache/cache.py
tests/__init__.py
tests/find_env.py
tests/test.py
pg_cache-0.1.6.6.dist-info/LICENSE
pg_cache-0.1.6.6.dist-info/METADATA
pg_cache-0.1.6.6.dist-info/WHEEL
pg_cache-0.1.6.6.dist-info/top_level.txt
pg_cache-0.1.6.6.dist-info/RECORD
