Metadata-Version: 2.1
Name: pg-cache
Version: 0.1.6.6
Summary: A PostgreSQL wrapper similar to diskcache
Home-page: https://github.com/li-xiu-qi/pg-cache
Author: li-xiu-qi
Author-email: lixiuqixiaoke@qq.com
Classifier: Programming Language :: Python :: 3
Classifier: License :: OSI Approved :: MIT License
Classifier: Operating System :: OS Independent
Requires-Python: >=3.6
License-File: LICENSE
Requires-Dist: sqlalchemy >=1.4
Requires-Dist: asyncpg >=0.21
